newapi/__init__.py
newapi/__main__.py
newapi/enums.py
newapi/response_models.py
newapi/router.py
newapi/server.py
newapi-0.1.0.dist-info/WHEEL
newapi-0.1.0.dist-info/METADATA
newapi-0.1.0.dist-info/RECORD
